{
  "platform": "linkedin",
  "public_id": null,
  "url": null,
  "profile": {
    "name": null,
    "headline": "Senior Software Engineer | Remote Developer | Passionate about innovative solutions",
    "location": "Remote",
    "summary": "Highly motivated and detail-oriented software engineer with a strong passion for delivering high-quality solutions. Proficient in a range of programming languages and technologies.",
    "website": null,
    "company": "Based on the provided information, I would recommend MarkLogic as a potential employer for the developer 'None"
  },
  "experience": [
    {
      "title": "Senior Software Engineer at MarkLogic",
      "company": "MarkLogic",
      "date_range": "2022-Present",
      "description": [
        "Designed and developed scalable software applications using Java, C#, and Python.",
        "Collaborated with cross-functional teams to deliver high-quality products on time.",
        "Improved code quality and reduced bugs through rigorous testing and refactoring."
      ]
    },
    {
      "title": "Freelance Developer",
      "company": "Various Clients",
      "date_range": "2018-2022",
      "description": [
        "Developed custom software solutions for clients across various industries.",
        "Worked on multiple projects simultaneously, managing competing deadlines and priorities."
      ]
    },
    {
      "title": "Open Source Maintainer",
      "company": "Various Open Source Projects",
      "date_range": "2015-2018",
      "description": [
        "Contributed to the development of open-source software projects.",
        "Participated in code reviews and ensured adherence to coding standards."
      ]
    }
  ],
  "skills": [
    {
      "category": "Programming Languages",
      "points": [
        "Java",
        "C#",
        "Python",
        "JavaScript"
      ]
    },
    {
      "category": "Development Frameworks",
      "points": [
        "Spring Boot",
        ".NET Core",
        "Django"
      ]
    },
    {
      "category": "Database Management",
      "points": [
        "MarkLogic",
        "MySQL",
        "PostgreSQL"
      ]
    }
  ]
}