{
  "platform": "twitter",
  "handle": "wagoodman",
  "url": null,
  "profile": {
    "name": "Alex Goodman",
    "bio": "Container Image Security & Go enthusiast | Vulnerability Scanning expert | Collaborative developer",
    "location": "Alexandria, VA",
    "website": null,
    "company": "@anchore ",
    "verified": false
  },
  "content_analysis": {
    "primary_topics": [
      "Container Image Security",
      "Go Programming Language",
      "Vulnerability Scanning"
    ],
    "posting_style": "Informative and conversational",
    "common_arguments": "Explaining technical concepts, sharing knowledge, and engaging with the community"
  },
  "audience_insight": null
}